nvd_sqlite3/__init__.py
nvd_sqlite3/process.py
nvd_sqlite3-0.1.1.dist-info/METADATA
nvd_sqlite3-0.1.1.dist-info/WHEEL
nvd_sqlite3-0.1.1.dist-info/entry_points.txt
nvd_sqlite3-0.1.1.dist-info/RECORD
