Metadata-Version: 2.1
Name: nvd-sqlite3
Version: 0.1.1
Summary: 
Author: Cristiano Henrique
Author-email: cristianovisk@gmail.com
Requires-Python: >=3.10,<4.0
Classifier: Programming Language :: Python :: 3
Classifier: Programming Language :: Python :: 3.10
Classifier: Programming Language :: Python :: 3.11
Requires-Dist: pandas (>=2.2.0,<3.0.0)
Requires-Dist: pyarrow (>=15.0.0,<16.0.0)
Requires-Dist: requests (>=2.31.0,<3.0.0)
